demo_uc_setup/__init__.py
demo_uc_setup/common.py
demo_uc_setup/config.py
demo_uc_setup/unity_catalog_setup.py
demo_uc_setup/unity_catalog_teardown.py
demo_uc_setup-0.1.0.dist-info/METADATA
demo_uc_setup-0.1.0.dist-info/WHEEL
demo_uc_setup-0.1.0.dist-info/RECORD
