Metadata-Version: 2.4
Name: demo_uc_setup
Version: 0.1.0
Summary: A reusable task-based framework for managing Unity Catalog in Databricks
Requires-Python: >=3.11
Requires-Dist: databricks-connect>=16.1.1
Requires-Dist: databricks-sdk>=0.44.1
Requires-Dist: pydantic-settings>=2.8.0
Requires-Dist: pydantic>=2.10.6
